{
  "@context": "http://iiif.io/api/presentation/3/context.json",
  "id": "https://iiif-metadata.perseus.tufts.edu/aa_5331/manifest.json",
  "type": "Manifest",
  "label": {
    "en": [
      "Harvard 1950.162"
    ]
  },
  "metadata": [
    {
      "label": {
        "en": [
          "thumbnail"
        ]
      },
      "value": {
        "en": [
          "https://iiif.perseus.tufts.edu/iiif/3/1990.01.1253/full/pct:20/0/default.png"
        ]
      }
    }
  ],
  "thumbnail": [
    {
      "id": "https://iiif.perseus.tufts.edu/iiif/3/1990.01.1253/full/pct:20/0/default.png",
      "type": "Image"
    }
  ],
  "items": [
    {
      "id": "https://iiif-metadata.perseus.tufts.edu/aa_5331/p1",
      "type": "Canvas",
      "label": {
        "en": [
          "Overview: handle left",
          "Photograph by Maria Daniels, courtesy of Harvard University Art Museums"
        ]
      },
      "height": 2396,
      "width": 1993,
      "items": [
        {
          "id": "http://example.org/iiif/23288",
          "type": "AnnotationPage",
          "items": [
            {
              "id": "http://example.org/iiif/23287",
              "type": "Annotation",
              "motivation": "painting",
              "body": {
                "id": "https://iiif.perseus.tufts.edu/iiif/3/1990.01.1253/full/max/0/default.jpg",
                "type": "Image",
                "height": 2396,
                "width": 1993,
                "service": [
                  {
                    "id": "https://iiif.perseus.tufts.edu/iiif/3/1990.01.1253",
                    "type": "ImageService3",
                    "profile": "level2"
                  }
                ],
                "format": "image/jpeg"
              },
              "target": "https://iiif-metadata.perseus.tufts.edu/aa_5331/p1"
            }
          ]
        }
      ]
    },
    {
      "id": "https://iiif-metadata.perseus.tufts.edu/aa_5331/p2",
      "type": "Canvas",
      "label": {
        "en": [
          "Overview: handle rear",
          "Photograph by Maria Daniels, courtesy of Harvard University Art Museums"
        ]
      },
      "height": 2396,
      "width": 2029,
      "items": [
        {
          "id": "http://example.org/iiif/23290",
          "type": "AnnotationPage",
          "items": [
            {
              "id": "http://example.org/iiif/23289",
              "type": "Annotation",
              "motivation": "painting",
              "body": {
                "id": "https://iiif.perseus.tufts.edu/iiif/3/1990.01.1254/full/max/0/default.jpg",
                "type": "Image",
                "height": 2396,
                "width": 2029,
                "service": [
                  {
                    "id": "https://iiif.perseus.tufts.edu/iiif/3/1990.01.1254",
                    "type": "ImageService3",
                    "profile": "level2"
                  }
                ],
                "format": "image/jpeg"
              },
              "target": "https://iiif-metadata.perseus.tufts.edu/aa_5331/p2"
            }
          ]
        }
      ]
    },
    {
      "id": "https://iiif-metadata.perseus.tufts.edu/aa_5331/p3",
      "type": "Canvas",
      "label": {
        "en": [
          "Main panel: woman between two bearded sirens",
          "Photograph by Maria Daniels, courtesy of Harvard University Art Museums"
        ]
      },
      "height": 2998,
      "width": 2020,
      "items": [
        {
          "id": "http://example.org/iiif/23292",
          "type": "AnnotationPage",
          "items": [
            {
              "id": "http://example.org/iiif/23291",
              "type": "Annotation",
              "motivation": "painting",
              "body": {
                "id": "https://iiif.perseus.tufts.edu/iiif/3/1990.01.1255/full/max/0/default.jpg",
                "type": "Image",
                "height": 2998,
                "width": 2020,
                "service": [
                  {
                    "id": "https://iiif.perseus.tufts.edu/iiif/3/1990.01.1255",
                    "type": "ImageService3",
                    "profile": "level2"
                  }
                ],
                "format": "image/jpeg"
              },
              "target": "https://iiif-metadata.perseus.tufts.edu/aa_5331/p3"
            }
          ]
        }
      ]
    },
    {
      "id": "https://iiif-metadata.perseus.tufts.edu/aa_5331/p4",
      "type": "Canvas",
      "label": {
        "en": [
          "Main panel: woman, upper half",
          "Photograph by Maria Daniels, courtesy of Harvard University Art Museums"
        ]
      },
      "height": 3005,
      "width": 2015,
      "items": [
        {
          "id": "http://example.org/iiif/23294",
          "type": "AnnotationPage",
          "items": [
            {
              "id": "http://example.org/iiif/23293",
              "type": "Annotation",
              "motivation": "painting",
              "body": {
                "id": "https://iiif.perseus.tufts.edu/iiif/3/1990.01.1256/full/max/0/default.jpg",
                "type": "Image",
                "height": 3005,
                "width": 2015,
                "service": [
                  {
                    "id": "https://iiif.perseus.tufts.edu/iiif/3/1990.01.1256",
                    "type": "ImageService3",
                    "profile": "level2"
                  }
                ],
                "format": "image/jpeg"
              },
              "target": "https://iiif-metadata.perseus.tufts.edu/aa_5331/p4"
            }
          ]
        }
      ]
    },
    {
      "id": "https://iiif-metadata.perseus.tufts.edu/aa_5331/p5",
      "type": "Canvas",
      "label": {
        "en": [
          "Main panel: woman, lower half",
          "Photograph by Maria Daniels, courtesy of Harvard University Art Museums"
        ]
      },
      "height": 2851,
      "width": 2030,
      "items": [
        {
          "id": "http://example.org/iiif/23296",
          "type": "AnnotationPage",
          "items": [
            {
              "id": "http://example.org/iiif/23295",
              "type": "Annotation",
              "motivation": "painting",
              "body": {
                "id": "https://iiif.perseus.tufts.edu/iiif/3/1990.01.1257/full/max/0/default.jpg",
                "type": "Image",
                "height": 2851,
                "width": 2030,
                "service": [
                  {
                    "id": "https://iiif.perseus.tufts.edu/iiif/3/1990.01.1257",
                    "type": "ImageService3",
                    "profile": "level2"
                  }
                ],
                "format": "image/jpeg"
              },
              "target": "https://iiif-metadata.perseus.tufts.edu/aa_5331/p5"
            }
          ]
        }
      ]
    },
    {
      "id": "https://iiif-metadata.perseus.tufts.edu/aa_5331/p6",
      "type": "Canvas",
      "label": {
        "en": [
          "Main panel: woman's arm",
          "Photograph by Maria Daniels, courtesy of Harvard University Art Museums"
        ]
      },
      "height": 3016,
      "width": 2030,
      "items": [
        {
          "id": "http://example.org/iiif/23298",
          "type": "AnnotationPage",
          "items": [
            {
              "id": "http://example.org/iiif/23297",
              "type": "Annotation",
              "motivation": "painting",
              "body": {
                "id": "https://iiif.perseus.tufts.edu/iiif/3/1990.01.1258/full/max/0/default.jpg",
                "type": "Image",
                "height": 3016,
                "width": 2030,
                "service": [
                  {
                    "id": "https://iiif.perseus.tufts.edu/iiif/3/1990.01.1258",
                    "type": "ImageService3",
                    "profile": "level2"
                  }
                ],
                "format": "image/jpeg"
              },
              "target": "https://iiif-metadata.perseus.tufts.edu/aa_5331/p6"
            }
          ]
        }
      ]
    },
    {
      "id": "https://iiif-metadata.perseus.tufts.edu/aa_5331/p7",
      "type": "Canvas",
      "label": {
        "en": [
          "Main panel: head of woman",
          "Photograph by Maria Daniels, courtesy of Harvard University Art Museums"
        ]
      },
      "height": 2985,
      "width": 2015,
      "items": [
        {
          "id": "http://example.org/iiif/23300",
          "type": "AnnotationPage",
          "items": [
            {
              "id": "http://example.org/iiif/23299",
              "type": "Annotation",
              "motivation": "painting",
              "body": {
                "id": "https://iiif.perseus.tufts.edu/iiif/3/1990.01.1259/full/max/0/default.jpg",
                "type": "Image",
                "height": 2985,
                "width": 2015,
                "service": [
                  {
                    "id": "https://iiif.perseus.tufts.edu/iiif/3/1990.01.1259",
                    "type": "ImageService3",
                    "profile": "level2"
                  }
                ],
                "format": "image/jpeg"
              },
              "target": "https://iiif-metadata.perseus.tufts.edu/aa_5331/p7"
            }
          ]
        }
      ]
    },
    {
      "id": "https://iiif-metadata.perseus.tufts.edu/aa_5331/p8",
      "type": "Canvas",
      "label": {
        "en": [
          "Main panel: siren left of woman",
          "Photograph by Maria Daniels, courtesy of Harvard University Art Museums"
        ]
      },
      "height": 2030,
      "width": 2289,
      "items": [
        {
          "id": "http://example.org/iiif/23302",
          "type": "AnnotationPage",
          "items": [
            {
              "id": "http://example.org/iiif/23301",
              "type": "Annotation",
              "motivation": "painting",
              "body": {
                "id": "https://iiif.perseus.tufts.edu/iiif/3/1990.01.1260/full/max/0/default.jpg",
                "type": "Image",
                "height": 2030,
                "width": 2289,
                "service": [
                  {
                    "id": "https://iiif.perseus.tufts.edu/iiif/3/1990.01.1260",
                    "type": "ImageService3",
                    "profile": "level2"
                  }
                ],
                "format": "image/jpeg"
              },
              "target": "https://iiif-metadata.perseus.tufts.edu/aa_5331/p8"
            }
          ]
        }
      ]
    },
    {
      "id": "https://iiif-metadata.perseus.tufts.edu/aa_5331/p9",
      "type": "Canvas",
      "label": {
        "en": [
          "Main panel: head of siren left of woman",
          "Photograph by Maria Daniels, courtesy of Harvard University Art Museums"
        ]
      },
      "height": 2974,
      "width": 2010,
      "items": [
        {
          "id": "http://example.org/iiif/23304",
          "type": "AnnotationPage",
          "items": [
            {
              "id": "http://example.org/iiif/23303",
              "type": "Annotation",
              "motivation": "painting",
              "body": {
                "id": "https://iiif.perseus.tufts.edu/iiif/3/1990.01.1261/full/max/0/default.jpg",
                "type": "Image",
                "height": 2974,
                "width": 2010,
                "service": [
                  {
                    "id": "https://iiif.perseus.tufts.edu/iiif/3/1990.01.1261",
                    "type": "ImageService3",
                    "profile": "level2"
                  }
                ],
                "format": "image/jpeg"
              },
              "target": "https://iiif-metadata.perseus.tufts.edu/aa_5331/p9"
            }
          ]
        }
      ]
    },
    {
      "id": "https://iiif-metadata.perseus.tufts.edu/aa_5331/p10",
      "type": "Canvas",
      "label": {
        "en": [
          "Main panel: siren left of woman, upper half",
          "Photograph by Maria Daniels, courtesy of Harvard University Art Museums"
        ]
      },
      "height": 3016,
      "width": 2010,
      "items": [
        {
          "id": "http://example.org/iiif/23306",
          "type": "AnnotationPage",
          "items": [
            {
              "id": "http://example.org/iiif/23305",
              "type": "Annotation",
              "motivation": "painting",
              "body": {
                "id": "https://iiif.perseus.tufts.edu/iiif/3/1990.01.1262/full/max/0/default.jpg",
                "type": "Image",
                "height": 3016,
                "width": 2010,
                "service": [
                  {
                    "id": "https://iiif.perseus.tufts.edu/iiif/3/1990.01.1262",
                    "type": "ImageService3",
                    "profile": "level2"
                  }
                ],
                "format": "image/jpeg"
              },
              "target": "https://iiif-metadata.perseus.tufts.edu/aa_5331/p10"
            }
          ]
        }
      ]
    },
    {
      "id": "https://iiif-metadata.perseus.tufts.edu/aa_5331/p11",
      "type": "Canvas",
      "label": {
        "en": [
          "Main panel: siren right of woman",
          "Photograph by Maria Daniels, courtesy of Harvard University Art Museums"
        ]
      },
      "height": 2025,
      "width": 2325,
      "items": [
        {
          "id": "http://example.org/iiif/23308",
          "type": "AnnotationPage",
          "items": [
            {
              "id": "http://example.org/iiif/23307",
              "type": "Annotation",
              "motivation": "painting",
              "body": {
                "id": "https://iiif.perseus.tufts.edu/iiif/3/1990.01.1263/full/max/0/default.jpg",
                "type": "Image",
                "height": 2025,
                "width": 2325,
                "service": [
                  {
                    "id": "https://iiif.perseus.tufts.edu/iiif/3/1990.01.1263",
                    "type": "ImageService3",
                    "profile": "level2"
                  }
                ],
                "format": "image/jpeg"
              },
              "target": "https://iiif-metadata.perseus.tufts.edu/aa_5331/p11"
            }
          ]
        }
      ]
    },
    {
      "id": "https://iiif-metadata.perseus.tufts.edu/aa_5331/p12",
      "type": "Canvas",
      "label": {
        "en": [
          "Main panel: siren right of woman",
          "Photograph by Maria Daniels, courtesy of Harvard University Art Museums"
        ]
      },
      "height": 2025,
      "width": 2985,
      "items": [
        {
          "id": "http://example.org/iiif/23310",
          "type": "AnnotationPage",
          "items": [
            {
              "id": "http://example.org/iiif/23309",
              "type": "Annotation",
              "motivation": "painting",
              "body": {
                "id": "https://iiif.perseus.tufts.edu/iiif/3/1990.01.1264/full/max/0/default.jpg",
                "type": "Image",
                "height": 2025,
                "width": 2985,
                "service": [
                  {
                    "id": "https://iiif.perseus.tufts.edu/iiif/3/1990.01.1264",
                    "type": "ImageService3",
                    "profile": "level2"
                  }
                ],
                "format": "image/jpeg"
              },
              "target": "https://iiif-metadata.perseus.tufts.edu/aa_5331/p12"
            }
          ]
        }
      ]
    },
    {
      "id": "https://iiif-metadata.perseus.tufts.edu/aa_5331/p13",
      "type": "Canvas",
      "label": {
        "en": [
          "Main panel: siren right of woman",
          "Photograph by Maria Daniels, courtesy of Harvard University Art Museums"
        ]
      },
      "height": 3005,
      "width": 2020,
      "items": [
        {
          "id": "http://example.org/iiif/23312",
          "type": "AnnotationPage",
          "items": [
            {
              "id": "http://example.org/iiif/23311",
              "type": "Annotation",
              "motivation": "painting",
              "body": {
                "id": "https://iiif.perseus.tufts.edu/iiif/3/1990.01.1265/full/max/0/default.jpg",
                "type": "Image",
                "height": 3005,
                "width": 2020,
                "service": [
                  {
                    "id": "https://iiif.perseus.tufts.edu/iiif/3/1990.01.1265",
                    "type": "ImageService3",
                    "profile": "level2"
                  }
                ],
                "format": "image/jpeg"
              },
              "target": "https://iiif-metadata.perseus.tufts.edu/aa_5331/p13"
            }
          ]
        }
      ]
    },
    {
      "id": "https://iiif-metadata.perseus.tufts.edu/aa_5331/p14",
      "type": "Canvas",
      "label": {
        "en": [
          "Main panel: head of siren right of woman",
          "Photograph by Maria Daniels, courtesy of Harvard University Art Museums"
        ]
      },
      "height": 3000,
      "width": 2020,
      "items": [
        {
          "id": "http://example.org/iiif/23314",
          "type": "AnnotationPage",
          "items": [
            {
              "id": "http://example.org/iiif/23313",
              "type": "Annotation",
              "motivation": "painting",
              "body": {
                "id": "https://iiif.perseus.tufts.edu/iiif/3/1990.01.1266/full/max/0/default.jpg",
                "type": "Image",
                "height": 3000,
                "width": 2020,
                "service": [
                  {
                    "id": "https://iiif.perseus.tufts.edu/iiif/3/1990.01.1266",
                    "type": "ImageService3",
                    "profile": "level2"
                  }
                ],
                "format": "image/jpeg"
              },
              "target": "https://iiif-metadata.perseus.tufts.edu/aa_5331/p14"
            }
          ]
        }
      ]
    },
    {
      "id": "https://iiif-metadata.perseus.tufts.edu/aa_5331/p15",
      "type": "Canvas",
      "label": {
        "en": [
          "Main panel: floral decoration",
          "Photograph by Maria Daniels, courtesy of Harvard University Art Museums"
        ]
      },
      "height": 2985,
      "width": 2005,
      "items": [
        {
          "id": "http://example.org/iiif/23316",
          "type": "AnnotationPage",
          "items": [
            {
              "id": "http://example.org/iiif/23315",
              "type": "Annotation",
              "motivation": "painting",
              "body": {
                "id": "https://iiif.perseus.tufts.edu/iiif/3/1990.01.1267/full/max/0/default.jpg",
                "type": "Image",
                "height": 2985,
                "width": 2005,
                "service": [
                  {
                    "id": "https://iiif.perseus.tufts.edu/iiif/3/1990.01.1267",
                    "type": "ImageService3",
                    "profile": "level2"
                  }
                ],
                "format": "image/jpeg"
              },
              "target": "https://iiif-metadata.perseus.tufts.edu/aa_5331/p15"
            }
          ]
        }
      ]
    },
    {
      "id": "https://iiif-metadata.perseus.tufts.edu/aa_5331/p16",
      "type": "Canvas",
      "label": {
        "en": [
          "Shoulder and rim: view from above",
          "Photograph by Maria Daniels, courtesy of Harvard University Art Museums"
        ]
      },
      "height": 2727,
      "width": 2010,
      "items": [
        {
          "id": "http://example.org/iiif/23318",
          "type": "AnnotationPage",
          "items": [
            {
              "id": "http://example.org/iiif/23317",
              "type": "Annotation",
              "motivation": "painting",
              "body": {
                "id": "https://iiif.perseus.tufts.edu/iiif/3/1990.01.1268/full/max/0/default.jpg",
                "type": "Image",
                "height": 2727,
                "width": 2010,
                "service": [
                  {
                    "id": "https://iiif.perseus.tufts.edu/iiif/3/1990.01.1268",
                    "type": "ImageService3",
                    "profile": "level2"
                  }
                ],
                "format": "image/jpeg"
              },
              "target": "https://iiif-metadata.perseus.tufts.edu/aa_5331/p16"
            }
          ]
        }
      ]
    }
  ]
}
