{
  "@context": "http://iiif.io/api/presentation/3/context.json",
  "id": "https://www.perseus.tufts.edu/api/aa_4988",
  "type": "Manifest",
  "label": {
    "en": [
      "Wrzburg L 521"
    ]
  },
  "metadata": [
    {
      "label": {
        "en": [
          "collection_history"
        ]
      },
      "value": {
        "en": [
          "<P>From the Feoli Collection</P>"
        ]
      }
    },
    {
      "label": {
        "en": [
          "date_for_sort"
        ]
      },
      "value": {
        "en": [
          "-435"
        ]
      }
    },
    {
      "label": {
        "en": [
          "dimensions"
        ]
      },
      "value": {
        "en": [
          "<P>H. 0.391 m.</P>"
        ]
      }
    },
    {
      "label": {
        "en": [
          "end_date"
        ]
      },
      "value": {
        "en": [
          "-430"
        ]
      }
    },
    {
      "label": {
        "en": [
          "end_mod"
        ]
      },
      "value": {
        "en": [
          "ca."
        ]
      }
    },
    {
      "label": {
        "en": [
          "entered_by"
        ]
      },
      "value": {
        "en": [
          "Ftima Dez"
        ]
      }
    },
    {
      "label": {
        "en": [
          "id"
        ]
      },
      "value": {
        "en": [
          "aa_4988"
        ]
      }
    },
    {
      "label": {
        "en": [
          "location"
        ]
      },
      "value": {
        "en": [
          "Perseus"
        ]
      }
    },
    {
      "label": {
        "en": [
          "name"
        ]
      },
      "value": {
        "en": [
          "Wrzburg L 521"
        ]
      }
    },
    {
      "label": {
        "en": [
          "other_bibliography"
        ]
      },
      "value": {
        "en": [
          "<P><bibl>Wegner, Das Musikleben der Griechen, 1949,\n      20</bibl>; <bibl>Simon, Gnomon 44, 1972, 421.</bibl>; <bibl>Beck 1975,\n      pl. 83. 404</bibl>; <bibl>CVA, 2, pls. 19.5-11</bibl>; <bibl>Moon\n      1983, 219, fig. 14.24</bibl>; <bibl>Paquette 1984, 129</bibl>;\n      <bibl>Keuls 1985, 126, fig. 11</bibl>.</P>"
        ]
      }
    },
    {
      "label": {
        "en": [
          "painter"
        ]
      },
      "value": {
        "en": [
          "Christie Painter"
        ]
      }
    },
    {
      "label": {
        "en": [
          "painter_mod"
        ]
      },
      "value": {
        "en": [
          "Attributed to the"
        ]
      }
    },
    {
      "label": {
        "en": [
          "period"
        ]
      },
      "value": {
        "en": [
          "High Classical"
        ]
      }
    },
    {
      "label": {
        "en": [
          "period_for_sort"
        ]
      },
      "value": {
        "en": [
          "40. Classical"
        ]
      }
    },
    {
      "label": {
        "en": [
          "perseus_version"
        ]
      },
      "value": {
        "en": [
          "2"
        ]
      }
    },
    {
      "label": {
        "en": [
          "primary_citation"
        ]
      },
      "value": {
        "en": [
          "<bibl>ARV2, 1046, 7</bibl>; <bibl>Beazley Addenda 2,\n      320</bibl>."
        ]
      }
    },
    {
      "label": {
        "en": [
          "shape"
        ]
      },
      "value": {
        "en": [
          "Calyx krater"
        ]
      }
    },
    {
      "label": {
        "en": [
          "sources_used"
        ]
      },
      "value": {
        "en": [
          "<P><bibl>Simon 1975b, 140</bibl>.</P>"
        ]
      }
    },
    {
      "label": {
        "en": [
          "start_date"
        ]
      },
      "value": {
        "en": [
          "-440"
        ]
      }
    },
    {
      "label": {
        "en": [
          "start_mod"
        ]
      },
      "value": {
        "en": [
          "ca."
        ]
      }
    },
    {
      "label": {
        "en": [
          "type"
        ]
      },
      "value": {
        "en": [
          "Vase"
        ]
      }
    },
    {
      "label": {
        "en": [
          "ware"
        ]
      },
      "value": {
        "en": [
          "Attic Red Figure"
        ]
      }
    }
  ],
  "items": [
    {
      "id": "http://example.org/iiif/11959",
      "type": "Canvas",
      "label": {
        "en": [
          "Photograph by Maria Daniels, courtesy of the Martin von Wagner Museum, Wrzburg",
          "Side A: overview."
        ]
      },
      "height": 315,
      "width": 282,
      "items": [
        {
          "id": "http://example.org/iiif/11961",
          "type": "AnnotationPage",
          "items": [
            {
              "id": "http://example.org/iiif/11960",
              "type": "Annotation",
              "motivation": "painting",
              "body": {
                "id": "https://iiif-dev.perseus.tufts.edu/iiif/3/1992.09.0312/full/max/0/default.jpg",
                "type": "Image",
                "height": 315,
                "width": 282,
                "service": [
                  {
                    "id": "https://iiif-dev.perseus.tufts.edu/iiif/3/1992.09.0312",
                    "type": "ImageService3",
                    "profile": "level2"
                  }
                ],
                "format": "image/jpeg"
              },
              "target": "http://example.org/iiif/11959"
            }
          ]
        }
      ]
    },
    {
      "id": "http://example.org/iiif/11962",
      "type": "Canvas",
      "label": {
        "en": [
          "Photograph by Maria Daniels, courtesy of the Martin von Wagner Museum, Wrzburg",
          "Side A: oblique view from right."
        ]
      },
      "height": 317,
      "width": 284,
      "items": [
        {
          "id": "http://example.org/iiif/11964",
          "type": "AnnotationPage",
          "items": [
            {
              "id": "http://example.org/iiif/11963",
              "type": "Annotation",
              "motivation": "painting",
              "body": {
                "id": "https://iiif-dev.perseus.tufts.edu/iiif/3/1992.09.0313/full/max/0/default.jpg",
                "type": "Image",
                "height": 317,
                "width": 284,
                "service": [
                  {
                    "id": "https://iiif-dev.perseus.tufts.edu/iiif/3/1992.09.0313",
                    "type": "ImageService3",
                    "profile": "level2"
                  }
                ],
                "format": "image/jpeg"
              },
              "target": "http://example.org/iiif/11962"
            }
          ]
        }
      ]
    },
    {
      "id": "http://example.org/iiif/11965",
      "type": "Canvas",
      "label": {
        "en": [
          "Handle, side A at left.",
          "Photograph by Maria Daniels, courtesy of the Martin von Wagner Museum, Wrzburg"
        ]
      },
      "height": 326,
      "width": 286,
      "items": [
        {
          "id": "http://example.org/iiif/11967",
          "type": "AnnotationPage",
          "items": [
            {
              "id": "http://example.org/iiif/11966",
              "type": "Annotation",
              "motivation": "painting",
              "body": {
                "id": "https://iiif-dev.perseus.tufts.edu/iiif/3/1992.09.0314/full/max/0/default.jpg",
                "type": "Image",
                "height": 326,
                "width": 286,
                "service": [
                  {
                    "id": "https://iiif-dev.perseus.tufts.edu/iiif/3/1992.09.0314",
                    "type": "ImageService3",
                    "profile": "level2"
                  }
                ],
                "format": "image/jpeg"
              },
              "target": "http://example.org/iiif/11965"
            }
          ]
        }
      ]
    },
    {
      "id": "http://example.org/iiif/11968",
      "type": "Canvas",
      "label": {
        "en": [
          "Photograph by Maria Daniels, courtesy of the Martin von Wagner Museum, Wrzburg",
          "Side B: oblique view from left."
        ]
      },
      "height": 319,
      "width": 285,
      "items": [
        {
          "id": "http://example.org/iiif/11970",
          "type": "AnnotationPage",
          "items": [
            {
              "id": "http://example.org/iiif/11969",
              "type": "Annotation",
              "motivation": "painting",
              "body": {
                "id": "https://iiif-dev.perseus.tufts.edu/iiif/3/1992.09.0315/full/max/0/default.jpg",
                "type": "Image",
                "height": 319,
                "width": 285,
                "service": [
                  {
                    "id": "https://iiif-dev.perseus.tufts.edu/iiif/3/1992.09.0315",
                    "type": "ImageService3",
                    "profile": "level2"
                  }
                ],
                "format": "image/jpeg"
              },
              "target": "http://example.org/iiif/11968"
            }
          ]
        }
      ]
    },
    {
      "id": "http://example.org/iiif/11971",
      "type": "Canvas",
      "label": {
        "en": [
          "Photograph by Maria Daniels, courtesy of the Martin von Wagner Museum, Wrzburg",
          "Side B: overview."
        ]
      },
      "height": 315,
      "width": 283,
      "items": [
        {
          "id": "http://example.org/iiif/11973",
          "type": "AnnotationPage",
          "items": [
            {
              "id": "http://example.org/iiif/11972",
              "type": "Annotation",
              "motivation": "painting",
              "body": {
                "id": "https://iiif-dev.perseus.tufts.edu/iiif/3/1992.09.0316/full/max/0/default.jpg",
                "type": "Image",
                "height": 315,
                "width": 283,
                "service": [
                  {
                    "id": "https://iiif-dev.perseus.tufts.edu/iiif/3/1992.09.0316",
                    "type": "ImageService3",
                    "profile": "level2"
                  }
                ],
                "format": "image/jpeg"
              },
              "target": "http://example.org/iiif/11971"
            }
          ]
        }
      ]
    },
    {
      "id": "http://example.org/iiif/11974",
      "type": "Canvas",
      "label": {
        "en": [
          "Photograph by Maria Daniels, courtesy of the Martin von Wagner Museum, Wrzburg",
          "Side B: oblique view from right."
        ]
      },
      "height": 314,
      "width": 286,
      "items": [
        {
          "id": "http://example.org/iiif/11976",
          "type": "AnnotationPage",
          "items": [
            {
              "id": "http://example.org/iiif/11975",
              "type": "Annotation",
              "motivation": "painting",
              "body": {
                "id": "https://iiif-dev.perseus.tufts.edu/iiif/3/1992.09.0317/full/max/0/default.jpg",
                "type": "Image",
                "height": 314,
                "width": 286,
                "service": [
                  {
                    "id": "https://iiif-dev.perseus.tufts.edu/iiif/3/1992.09.0317",
                    "type": "ImageService3",
                    "profile": "level2"
                  }
                ],
                "format": "image/jpeg"
              },
              "target": "http://example.org/iiif/11974"
            }
          ]
        }
      ]
    },
    {
      "id": "http://example.org/iiif/11977",
      "type": "Canvas",
      "label": {
        "en": [
          "Handle, side A at right.",
          "Photograph by Maria Daniels, courtesy of the Martin von Wagner Museum, Wrzburg"
        ]
      },
      "height": 326,
      "width": 285,
      "items": [
        {
          "id": "http://example.org/iiif/11979",
          "type": "AnnotationPage",
          "items": [
            {
              "id": "http://example.org/iiif/11978",
              "type": "Annotation",
              "motivation": "painting",
              "body": {
                "id": "https://iiif-dev.perseus.tufts.edu/iiif/3/1992.09.0318/full/max/0/default.jpg",
                "type": "Image",
                "height": 326,
                "width": 285,
                "service": [
                  {
                    "id": "https://iiif-dev.perseus.tufts.edu/iiif/3/1992.09.0318",
                    "type": "ImageService3",
                    "profile": "level2"
                  }
                ],
                "format": "image/jpeg"
              },
              "target": "http://example.org/iiif/11977"
            }
          ]
        }
      ]
    },
    {
      "id": "http://example.org/iiif/11980",
      "type": "Canvas",
      "label": {
        "en": [
          "Photograph by Maria Daniels, courtesy of the Martin von Wagner Museum, Wrzburg",
          "Side A: oblique view from left."
        ]
      },
      "height": 310,
      "width": 280,
      "items": [
        {
          "id": "http://example.org/iiif/11982",
          "type": "AnnotationPage",
          "items": [
            {
              "id": "http://example.org/iiif/11981",
              "type": "Annotation",
              "motivation": "painting",
              "body": {
                "id": "https://iiif-dev.perseus.tufts.edu/iiif/3/1992.09.0319/full/max/0/default.jpg",
                "type": "Image",
                "height": 310,
                "width": 280,
                "service": [
                  {
                    "id": "https://iiif-dev.perseus.tufts.edu/iiif/3/1992.09.0319",
                    "type": "ImageService3",
                    "profile": "level2"
                  }
                ],
                "format": "image/jpeg"
              },
              "target": "http://example.org/iiif/11980"
            }
          ]
        }
      ]
    },
    {
      "id": "http://example.org/iiif/11983",
      "type": "Canvas",
      "label": {
        "en": [
          "Photograph by Maria Daniels, courtesy of the Martin von Wagner Museum, Wrzburg",
          "Side A: women playing music. Eros."
        ]
      },
      "height": 353,
      "width": 532,
      "items": [
        {
          "id": "http://example.org/iiif/11985",
          "type": "AnnotationPage",
          "items": [
            {
              "id": "http://example.org/iiif/11984",
              "type": "Annotation",
              "motivation": "painting",
              "body": {
                "id": "https://iiif-dev.perseus.tufts.edu/iiif/3/1992.09.0320/full/max/0/default.jpg",
                "type": "Image",
                "height": 353,
                "width": 532,
                "service": [
                  {
                    "id": "https://iiif-dev.perseus.tufts.edu/iiif/3/1992.09.0320",
                    "type": "ImageService3",
                    "profile": "level2"
                  }
                ],
                "format": "image/jpeg"
              },
              "target": "http://example.org/iiif/11983"
            }
          ]
        }
      ]
    },
    {
      "id": "http://example.org/iiif/11986",
      "type": "Canvas",
      "label": {
        "en": [
          "Photograph by Maria Daniels, courtesy of the Martin von Wagner Museum, Wrzburg",
          "Side A: woman standing at left."
        ]
      },
      "height": 356,
      "width": 237,
      "items": [
        {
          "id": "http://example.org/iiif/11988",
          "type": "AnnotationPage",
          "items": [
            {
              "id": "http://example.org/iiif/11987",
              "type": "Annotation",
              "motivation": "painting",
              "body": {
                "id": "https://iiif-dev.perseus.tufts.edu/iiif/3/1992.09.0321/full/max/0/default.jpg",
                "type": "Image",
                "height": 356,
                "width": 237,
                "service": [
                  {
                    "id": "https://iiif-dev.perseus.tufts.edu/iiif/3/1992.09.0321",
                    "type": "ImageService3",
                    "profile": "level2"
                  }
                ],
                "format": "image/jpeg"
              },
              "target": "http://example.org/iiif/11986"
            }
          ]
        }
      ]
    },
    {
      "id": "http://example.org/iiif/11989",
      "type": "Canvas",
      "label": {
        "en": [
          "Photograph by Maria Daniels, courtesy of the Martin von Wagner Museum, Wrzburg",
          "Side A: woman at left, detail of head and upper body."
        ]
      },
      "height": 353,
      "width": 538,
      "items": [
        {
          "id": "http://example.org/iiif/11991",
          "type": "AnnotationPage",
          "items": [
            {
              "id": "http://example.org/iiif/11990",
              "type": "Annotation",
              "motivation": "painting",
              "body": {
                "id": "https://iiif-dev.perseus.tufts.edu/iiif/3/1992.09.0322/full/max/0/default.jpg",
                "type": "Image",
                "height": 353,
                "width": 538,
                "service": [
                  {
                    "id": "https://iiif-dev.perseus.tufts.edu/iiif/3/1992.09.0322",
                    "type": "ImageService3",
                    "profile": "level2"
                  }
                ],
                "format": "image/jpeg"
              },
              "target": "http://example.org/iiif/11989"
            }
          ]
        }
      ]
    },
    {
      "id": "http://example.org/iiif/11992",
      "type": "Canvas",
      "label": {
        "en": [
          "Photograph by Maria Daniels, courtesy of the Martin von Wagner Museum, Wrzburg",
          "Side A: detail of taenia and crosslike object hanging on the wall."
        ]
      },
      "height": 351,
      "width": 536,
      "items": [
        {
          "id": "http://example.org/iiif/11994",
          "type": "AnnotationPage",
          "items": [
            {
              "id": "http://example.org/iiif/11993",
              "type": "Annotation",
              "motivation": "painting",
              "body": {
                "id": "https://iiif-dev.perseus.tufts.edu/iiif/3/1992.09.0323/full/max/0/default.jpg",
                "type": "Image",
                "height": 351,
                "width": 536,
                "service": [
                  {
                    "id": "https://iiif-dev.perseus.tufts.edu/iiif/3/1992.09.0323",
                    "type": "ImageService3",
                    "profile": "level2"
                  }
                ],
                "format": "image/jpeg"
              },
              "target": "http://example.org/iiif/11992"
            }
          ]
        }
      ]
    },
    {
      "id": "http://example.org/iiif/11995",
      "type": "Canvas",
      "label": {
        "en": [
          "Photograph by Maria Daniels, courtesy of the Martin von Wagner Museum, Wrzburg",
          "Side A: woman seated playing the lyre."
        ]
      },
      "height": 353,
      "width": 526,
      "items": [
        {
          "id": "http://example.org/iiif/11997",
          "type": "AnnotationPage",
          "items": [
            {
              "id": "http://example.org/iiif/11996",
              "type": "Annotation",
              "motivation": "painting",
              "body": {
                "id": "https://iiif-dev.perseus.tufts.edu/iiif/3/1992.09.0324/full/max/0/default.jpg",
                "type": "Image",
                "height": 353,
                "width": 526,
                "service": [
                  {
                    "id": "https://iiif-dev.perseus.tufts.edu/iiif/3/1992.09.0324",
                    "type": "ImageService3",
                    "profile": "level2"
                  }
                ],
                "format": "image/jpeg"
              },
              "target": "http://example.org/iiif/11995"
            }
          ]
        }
      ]
    },
    {
      "id": "http://example.org/iiif/11998",
      "type": "Canvas",
      "label": {
        "en": [
          "Photograph by Maria Daniels, courtesy of the Martin von Wagner Museum, Wrzburg",
          "Side A: woman playing lyre, detail of head and upper body."
        ]
      },
      "height": 350,
      "width": 538,
      "items": [
        {
          "id": "http://example.org/iiif/12000",
          "type": "AnnotationPage",
          "items": [
            {
              "id": "http://example.org/iiif/11999",
              "type": "Annotation",
              "motivation": "painting",
              "body": {
                "id": "https://iiif-dev.perseus.tufts.edu/iiif/3/1992.09.0325/full/max/0/default.jpg",
                "type": "Image",
                "height": 350,
                "width": 538,
                "service": [
                  {
                    "id": "https://iiif-dev.perseus.tufts.edu/iiif/3/1992.09.0325",
                    "type": "ImageService3",
                    "profile": "level2"
                  }
                ],
                "format": "image/jpeg"
              },
              "target": "http://example.org/iiif/11998"
            }
          ]
        }
      ]
    },
    {
      "id": "http://example.org/iiif/12001",
      "type": "Canvas",
      "label": {
        "en": [
          "Photograph by Maria Daniels, courtesy of the Martin von Wagner Museum, Wrzburg",
          "Side A: woman playing lyre, detail of head and upper body. Detail of relief."
        ]
      },
      "height": 400,
      "width": 550,
      "items": [
        {
          "id": "http://example.org/iiif/12003",
          "type": "AnnotationPage",
          "items": [
            {
              "id": "http://example.org/iiif/12002",
              "type": "Annotation",
              "motivation": "painting",
              "body": {
                "id": "https://iiif-dev.perseus.tufts.edu/iiif/3/1992.09.0326/full/max/0/default.jpg",
                "type": "Image",
                "height": 400,
                "width": 550,
                "service": [
                  {
                    "id": "https://iiif-dev.perseus.tufts.edu/iiif/3/1992.09.0326",
                    "type": "ImageService3",
                    "profile": "level2"
                  }
                ],
                "format": "image/jpeg"
              },
              "target": "http://example.org/iiif/12001"
            }
          ]
        }
      ]
    },
    {
      "id": "http://example.org/iiif/12004",
      "type": "Canvas",
      "label": {
        "en": [
          "Photograph by Maria Daniels, courtesy of the Martin von Wagner Museum, Wrzburg",
          "Side A: Eros."
        ]
      },
      "height": 350,
      "width": 536,
      "items": [
        {
          "id": "http://example.org/iiif/12006",
          "type": "AnnotationPage",
          "items": [
            {
              "id": "http://example.org/iiif/12005",
              "type": "Annotation",
              "motivation": "painting",
              "body": {
                "id": "https://iiif-dev.perseus.tufts.edu/iiif/3/1992.09.0327/full/max/0/default.jpg",
                "type": "Image",
                "height": 350,
                "width": 536,
                "service": [
                  {
                    "id": "https://iiif-dev.perseus.tufts.edu/iiif/3/1992.09.0327",
                    "type": "ImageService3",
                    "profile": "level2"
                  }
                ],
                "format": "image/jpeg"
              },
              "target": "http://example.org/iiif/12004"
            }
          ]
        }
      ]
    },
    {
      "id": "http://example.org/iiif/12007",
      "type": "Canvas",
      "label": {
        "en": [
          "Photograph by Maria Daniels, courtesy of the Martin von Wagner Museum, Wrzburg",
          "Side A: Eros, detail of head and body. Relief."
        ]
      },
      "height": 352,
      "width": 534,
      "items": [
        {
          "id": "http://example.org/iiif/12009",
          "type": "AnnotationPage",
          "items": [
            {
              "id": "http://example.org/iiif/12008",
              "type": "Annotation",
              "motivation": "painting",
              "body": {
                "id": "https://iiif-dev.perseus.tufts.edu/iiif/3/1992.09.0328/full/max/0/default.jpg",
                "type": "Image",
                "height": 352,
                "width": 534,
                "service": [
                  {
                    "id": "https://iiif-dev.perseus.tufts.edu/iiif/3/1992.09.0328",
                    "type": "ImageService3",
                    "profile": "level2"
                  }
                ],
                "format": "image/jpeg"
              },
              "target": "http://example.org/iiif/12007"
            }
          ]
        }
      ]
    },
    {
      "id": "http://example.org/iiif/12010",
      "type": "Canvas",
      "label": {
        "en": [
          "Photograph by Maria Daniels, courtesy of the Martin von Wagner Museum, Wrzburg",
          "Side A: woman at right."
        ]
      },
      "height": 357,
      "width": 236,
      "items": [
        {
          "id": "http://example.org/iiif/12012",
          "type": "AnnotationPage",
          "items": [
            {
              "id": "http://example.org/iiif/12011",
              "type": "Annotation",
              "motivation": "painting",
              "body": {
                "id": "https://iiif-dev.perseus.tufts.edu/iiif/3/1992.09.0329/full/max/0/default.jpg",
                "type": "Image",
                "height": 357,
                "width": 236,
                "service": [
                  {
                    "id": "https://iiif-dev.perseus.tufts.edu/iiif/3/1992.09.0329",
                    "type": "ImageService3",
                    "profile": "level2"
                  }
                ],
                "format": "image/jpeg"
              },
              "target": "http://example.org/iiif/12010"
            }
          ]
        }
      ]
    },
    {
      "id": "http://example.org/iiif/12013",
      "type": "Canvas",
      "label": {
        "en": [
          "Photograph by Maria Daniels, courtesy of the Martin von Wagner Museum, Wrzburg",
          "Side A: woman at right, detail of head and upper body."
        ]
      },
      "height": 350,
      "width": 532,
      "items": [
        {
          "id": "http://example.org/iiif/12015",
          "type": "AnnotationPage",
          "items": [
            {
              "id": "http://example.org/iiif/12014",
              "type": "Annotation",
              "motivation": "painting",
              "body": {
                "id": "https://iiif-dev.perseus.tufts.edu/iiif/3/1992.09.0330/full/max/0/default.jpg",
                "type": "Image",
                "height": 350,
                "width": 532,
                "service": [
                  {
                    "id": "https://iiif-dev.perseus.tufts.edu/iiif/3/1992.09.0330",
                    "type": "ImageService3",
                    "profile": "level2"
                  }
                ],
                "format": "image/jpeg"
              },
              "target": "http://example.org/iiif/12013"
            }
          ]
        }
      ]
    },
    {
      "id": "http://example.org/iiif/12016",
      "type": "Canvas",
      "label": {
        "en": [
          "Photograph by Maria Daniels, courtesy of the Martin von Wagner Museum, Wrzburg",
          "Side A: detail of aulos and lyre."
        ]
      },
      "height": 352,
      "width": 537,
      "items": [
        {
          "id": "http://example.org/iiif/12018",
          "type": "AnnotationPage",
          "items": [
            {
              "id": "http://example.org/iiif/12017",
              "type": "Annotation",
              "motivation": "painting",
              "body": {
                "id": "https://iiif-dev.perseus.tufts.edu/iiif/3/1992.09.0331/full/max/0/default.jpg",
                "type": "Image",
                "height": 352,
                "width": 537,
                "service": [
                  {
                    "id": "https://iiif-dev.perseus.tufts.edu/iiif/3/1992.09.0331",
                    "type": "ImageService3",
                    "profile": "level2"
                  }
                ],
                "format": "image/jpeg"
              },
              "target": "http://example.org/iiif/12016"
            }
          ]
        }
      ]
    },
    {
      "id": "http://example.org/iiif/12019",
      "type": "Canvas",
      "label": {
        "en": [
          "Photograph by Maria Daniels, courtesy of the Martin von Wagner Museum, Wrzburg",
          "Side A: cradle-kithara."
        ]
      },
      "height": 350,
      "width": 533,
      "items": [
        {
          "id": "http://example.org/iiif/12021",
          "type": "AnnotationPage",
          "items": [
            {
              "id": "http://example.org/iiif/12020",
              "type": "Annotation",
              "motivation": "painting",
              "body": {
                "id": "https://iiif-dev.perseus.tufts.edu/iiif/3/1992.09.0332/full/max/0/default.jpg",
                "type": "Image",
                "height": 350,
                "width": 533,
                "service": [
                  {
                    "id": "https://iiif-dev.perseus.tufts.edu/iiif/3/1992.09.0332",
                    "type": "ImageService3",
                    "profile": "level2"
                  }
                ],
                "format": "image/jpeg"
              },
              "target": "http://example.org/iiif/12019"
            }
          ]
        }
      ]
    },
    {
      "id": "http://example.org/iiif/12022",
      "type": "Canvas",
      "label": {
        "en": [
          "Photograph by Maria Daniels, courtesy of the Martin von Wagner Museum, Wrzburg",
          "Side B: three youths at the palaestra."
        ]
      },
      "height": 345,
      "width": 472,
      "items": [
        {
          "id": "http://example.org/iiif/12024",
          "type": "AnnotationPage",
          "items": [
            {
              "id": "http://example.org/iiif/12023",
              "type": "Annotation",
              "motivation": "painting",
              "body": {
                "id": "https://iiif-dev.perseus.tufts.edu/iiif/3/1992.09.0333/full/max/0/default.jpg",
                "type": "Image",
                "height": 345,
                "width": 472,
                "service": [
                  {
                    "id": "https://iiif-dev.perseus.tufts.edu/iiif/3/1992.09.0333",
                    "type": "ImageService3",
                    "profile": "level2"
                  }
                ],
                "format": "image/jpeg"
              },
              "target": "http://example.org/iiif/12022"
            }
          ]
        }
      ]
    },
    {
      "id": "http://example.org/iiif/12025",
      "type": "Canvas",
      "label": {
        "en": [
          "Photograph by Maria Daniels, courtesy of the Martin von Wagner Museum, Wrzburg",
          "Side B: youth with strigil."
        ]
      },
      "height": 353,
      "width": 231,
      "items": [
        {
          "id": "http://example.org/iiif/12027",
          "type": "AnnotationPage",
          "items": [
            {
              "id": "http://example.org/iiif/12026",
              "type": "Annotation",
              "motivation": "painting",
              "body": {
                "id": "https://iiif-dev.perseus.tufts.edu/iiif/3/1992.09.0334/full/max/0/default.jpg",
                "type": "Image",
                "height": 353,
                "width": 231,
                "service": [
                  {
                    "id": "https://iiif-dev.perseus.tufts.edu/iiif/3/1992.09.0334",
                    "type": "ImageService3",
                    "profile": "level2"
                  }
                ],
                "format": "image/jpeg"
              },
              "target": "http://example.org/iiif/12025"
            }
          ]
        }
      ]
    },
    {
      "id": "http://example.org/iiif/12028",
      "type": "Canvas",
      "label": {
        "en": [
          "Photograph by Maria Daniels, courtesy of the Martin von Wagner Museum, Wrzburg",
          "Side B: youth with strigil, detail of head and upper body."
        ]
      },
      "height": 350,
      "width": 531,
      "items": [
        {
          "id": "http://example.org/iiif/12030",
          "type": "AnnotationPage",
          "items": [
            {
              "id": "http://example.org/iiif/12029",
              "type": "Annotation",
              "motivation": "painting",
              "body": {
                "id": "https://iiif-dev.perseus.tufts.edu/iiif/3/1992.09.0335/full/max/0/default.jpg",
                "type": "Image",
                "height": 350,
                "width": 531,
                "service": [
                  {
                    "id": "https://iiif-dev.perseus.tufts.edu/iiif/3/1992.09.0335",
                    "type": "ImageService3",
                    "profile": "level2"
                  }
                ],
                "format": "image/jpeg"
              },
              "target": "http://example.org/iiif/12028"
            }
          ]
        }
      ]
    },
    {
      "id": "http://example.org/iiif/12031",
      "type": "Canvas",
      "label": {
        "en": [
          "Photograph by Maria Daniels, courtesy of the Martin von Wagner Museum, Wrzburg",
          "Side B: youth in the middle."
        ]
      },
      "height": 355,
      "width": 237,
      "items": [
        {
          "id": "http://example.org/iiif/12033",
          "type": "AnnotationPage",
          "items": [
            {
              "id": "http://example.org/iiif/12032",
              "type": "Annotation",
              "motivation": "painting",
              "body": {
                "id": "https://iiif-dev.perseus.tufts.edu/iiif/3/1992.09.0336/full/max/0/default.jpg",
                "type": "Image",
                "height": 355,
                "width": 237,
                "service": [
                  {
                    "id": "https://iiif-dev.perseus.tufts.edu/iiif/3/1992.09.0336",
                    "type": "ImageService3",
                    "profile": "level2"
                  }
                ],
                "format": "image/jpeg"
              },
              "target": "http://example.org/iiif/12031"
            }
          ]
        }
      ]
    },
    {
      "id": "http://example.org/iiif/12034",
      "type": "Canvas",
      "label": {
        "en": [
          "Photograph by Maria Daniels, courtesy of the Martin von Wagner Museum, Wrzburg",
          "Side B: youth in the middle, detail of head and body."
        ]
      },
      "height": 348,
      "width": 536,
      "items": [
        {
          "id": "http://example.org/iiif/12036",
          "type": "AnnotationPage",
          "items": [
            {
              "id": "http://example.org/iiif/12035",
              "type": "Annotation",
              "motivation": "painting",
              "body": {
                "id": "https://iiif-dev.perseus.tufts.edu/iiif/3/1992.09.0337/full/max/0/default.jpg",
                "type": "Image",
                "height": 348,
                "width": 536,
                "service": [
                  {
                    "id": "https://iiif-dev.perseus.tufts.edu/iiif/3/1992.09.0337",
                    "type": "ImageService3",
                    "profile": "level2"
                  }
                ],
                "format": "image/jpeg"
              },
              "target": "http://example.org/iiif/12034"
            }
          ]
        }
      ]
    },
    {
      "id": "http://example.org/iiif/12037",
      "type": "Canvas",
      "label": {
        "en": [
          "Photograph by Maria Daniels, courtesy of the Martin von Wagner Museum, Wrzburg",
          "Side B: youth at right."
        ]
      },
      "height": 357,
      "width": 237,
      "items": [
        {
          "id": "http://example.org/iiif/12039",
          "type": "AnnotationPage",
          "items": [
            {
              "id": "http://example.org/iiif/12038",
              "type": "Annotation",
              "motivation": "painting",
              "body": {
                "id": "https://iiif-dev.perseus.tufts.edu/iiif/3/1992.09.0338/full/max/0/default.jpg",
                "type": "Image",
                "height": 357,
                "width": 237,
                "service": [
                  {
                    "id": "https://iiif-dev.perseus.tufts.edu/iiif/3/1992.09.0338",
                    "type": "ImageService3",
                    "profile": "level2"
                  }
                ],
                "format": "image/jpeg"
              },
              "target": "http://example.org/iiif/12037"
            }
          ]
        }
      ]
    },
    {
      "id": "http://example.org/iiif/12040",
      "type": "Canvas",
      "label": {
        "en": [
          "Photograph by Maria Daniels, courtesy of the Martin von Wagner Museum, Wrzburg",
          "Side B: youth at right, detail of head and body."
        ]
      },
      "height": 352,
      "width": 537,
      "items": [
        {
          "id": "http://example.org/iiif/12042",
          "type": "AnnotationPage",
          "items": [
            {
              "id": "http://example.org/iiif/12041",
              "type": "Annotation",
              "motivation": "painting",
              "body": {
                "id": "https://iiif-dev.perseus.tufts.edu/iiif/3/1992.09.0339/full/max/0/default.jpg",
                "type": "Image",
                "height": 352,
                "width": 537,
                "service": [
                  {
                    "id": "https://iiif-dev.perseus.tufts.edu/iiif/3/1992.09.0339",
                    "type": "ImageService3",
                    "profile": "level2"
                  }
                ],
                "format": "image/jpeg"
              },
              "target": "http://example.org/iiif/12040"
            }
          ]
        }
      ]
    }
  ]
}
